{
    "Id": "playas-de-contenedores",
    "Title": "Playas de Contenedores",
    "Subtitle": "Desarrollo Logístico e Integración Urbana",
    "DescriptionTitle": "",
    "Description": "Con esta obra, Ushuaia avanza hacia un modelo de crecimiento ordenado y sostenible, donde la eficiencia portuaria se articula con la calidad de vida urbana, reforzando el perfil de la ciudad como capital logística de la Patagonia Austral en armonía con su entorno natural." ,
    "CarouselImageNames": [
        "infraestructura-productiva-y-conectividad_nueva-playa-de-contenedores-ushuaia"

    ],
    "PdfLinks": [
        {
            "Name": "",
            "Url": ""
        },
        {
            "Name": "",
            "Url": ""
        }
    ]
}