{
    "Id": "plantas-de-licuefacción",
    "Title": "Plantas de Licuefacción",
    "Subtitle": "Energía para el Futuro Fueguino",
    "DescriptionTitle": "",
    "Description": "La instalación de una planta de licuefacción en la zona de San Sebastián marcará un hito histórico para el desarrollo energético e industrial de Tierra del Fuego. \n\nEsta obra estratégica permitirá transformar el gas natural en líquido (GNL), facilitando su transporte eficiente y seguro hacia mercados nacionales e internacionales. \n\nEste proyecto representa una triple oportunidad para la Provincia: \n\n- Monetización de reservas: Agregará valor a los recursos energéticos fueguinos \n\n- Generación de empleo: Creará puestos de trabajo calificado y dinamizará la economía local \n\n- Integración global: Posicionará a Tierra del Fuego como exportador de energía en el mercado mundial \n\nLa planta de licuefacción se consolida así como una solución estratégica que transformará la matriz productiva provincial, generando desarrollo sostenible y soberanía energética para las futuras generaciones." ,
    
    "CarouselImageNames": [
        "infraestructura-productiva-y-conectividad_planta-de-licuefacción-san-sebastián"
        
    ],
    "PdfLinks": [
        {
            "Name": "",
            "Url": ""
        },
        {
            "Name": "",
            "Url": ""
        }
    ]
}